safer/__init__.py
safer/py.typed
safer-5.1.0.dist-info/LICENSE
safer-5.1.0.dist-info/METADATA
safer-5.1.0.dist-info/WHEEL
safer-5.1.0.dist-info/RECORD
