Metadata-Version: 2.1
Name: safer
Version: 5.1.0
Summary: 🧿 A safer writer for files and streams 🧿
Home-page: https://github.com/rec/safer
License: MIT
Author: Tom Ritchford
Author-email: tom@swirly.com
Requires-Python: >=3.8
Classifier: License :: OSI Approved :: MIT License
Classifier: Programming Language :: Python :: 3
Classifier: Programming Language :: Python :: 3.8
Classifier: Programming Language :: Python :: 3.9
Classifier: Programming Language :: Python :: 3.10
Classifier: Programming Language :: Python :: 3.11
Classifier: Programming Language :: Python :: 3.12
Project-URL: Documentation, https://rec.github.io/safer
Project-URL: Repository, https://github.com/rec/safer
